Flask_Stride-0.2.0.dist-info/DESCRIPTION.rst
Flask_Stride-0.2.0.dist-info/METADATA
Flask_Stride-0.2.0.dist-info/RECORD
Flask_Stride-0.2.0.dist-info/WHEEL
Flask_Stride-0.2.0.dist-info/metadata.json
Flask_Stride-0.2.0.dist-info/top_level.txt
flask_stride/__init__.py
flask_stride/chatbot.py
flask_stride/flask_stride.py
flask_stride/module.py
